btstrm/__init__.py
btstrm/__main__.py
btstrm/btstrm.py
btstrm-0.1.7.dist-info/LICENSE
btstrm-0.1.7.dist-info/METADATA
btstrm-0.1.7.dist-info/WHEEL
btstrm-0.1.7.dist-info/entry_points.txt
btstrm-0.1.7.dist-info/top_level.txt
btstrm-0.1.7.dist-info/RECORD
