Metadata-Version: 2.1
Name: btstrm
Version: 0.1.7
Summary: A script to stream torrents using BTFS
Author: asakura42
License: GPL-3
Project-URL: Homepage, https://github.com/asakura42/btstrm
Project-URL: Bug Tracker, https://github.com/asakura42/btstrm/issues
Keywords: torrent,streaming,btfs
Classifier: License :: OSI Approved :: GNU General Public License v3 (GPLv3)
Classifier: Programming Language :: Python :: 3
License-File: LICENSE
Requires-Dist: requests
Requires-Dist: tqdm
Requires-Dist: colorama
Requires-Dist: unidecode
Requires-Dist: beautifulsoup4
